sphinx_test_cases/__init__.py
sphinx_test_cases/autodoc_test.py
sphinx_test_cases/tests.py
sphinx_test_cases-0.5.dist-info/LICENSE
sphinx_test_cases-0.5.dist-info/METADATA
sphinx_test_cases-0.5.dist-info/WHEEL
sphinx_test_cases-0.5.dist-info/top_level.txt
sphinx_test_cases-0.5.dist-info/RECORD
