Metadata-Version: 2.1
Name: sphinx-test-cases
Version: 0.5
Summary: This package is a simple extention to the Sphinx, which is
Home-page: https://github.com/ArtUrim/sphinx-test
Author: Arturim
Author-email: lozinski.artur@gmail.com
License: Apache
Keywords: sphinx test case scenario plan
Platform: UNKNOWN
License-File: LICENSE
Requires-Dist: sphinx
Requires-Dist: wheel
